get_coupa_token.py
get_coupa_token-1.4.dist-info/METADATA
get_coupa_token-1.4.dist-info/WHEEL
get_coupa_token-1.4.dist-info/licenses/LICENSE
get_coupa_token-1.4.dist-info/RECORD
