Metadata-Version: 2.1
Name: get_coupa_token
Version: 1.4
Summary: A custom module to manage specific OAUTH workflow for Coupa platform
Author-email: Brodie Zambergs <brodie.zambergs@monash.edu>
License-File: LICENSE
Classifier: License :: OSI Approved :: MIT License
Classifier: Operating System :: OS Independent
Classifier: Programming Language :: Python :: 3
Requires-Python: >=3.7
